hd_glio/__init__.py
hd_glio/hd_glio_predict.py
hd_glio/hd_glio_predict_folder.py
hd_glio/paths.py
hd_glio/setup_hd_glio.py
hd_glio/utils.py
hd_glio-2.0.dist-info/LICENSE.txt
hd_glio-2.0.dist-info/METADATA
hd_glio-2.0.dist-info/WHEEL
hd_glio-2.0.dist-info/entry_points.txt
hd_glio-2.0.dist-info/top_level.txt
hd_glio-2.0.dist-info/RECORD
