Metadata-Version: 2.1
Name: hd-glio
Version: 2.0
Summary: Tool for brain tumor segmentation. This is the result of a joint project between the Department of Neuroradiology at the Heidelberg University Hospital and the Division of Medical Image Computing at the German Cancer Research Center (DKFZ). See readme.md for more information
Home-page: https://github.com/MIC-DKFZ/hd_glio
Author: Fabian Isensee
Author-email: f.isensee@dkfz.de
License: Apache 2.0
Platform: UNKNOWN
Classifier: Intended Audience :: Science/Research
Classifier: Programming Language :: Python
Classifier: Topic :: Scientific/Engineering
Classifier: Operating System :: Unix
Requires-Python: >=3.5
Requires-Dist: torch
Requires-Dist: numpy
Requires-Dist: scikit-image
Requires-Dist: SimpleITK
Requires-Dist: batchgenerators
Requires-Dist: nnunet (>=1.1.5)
